README
setup.py
appengine_mailer/__init__.py
appengine_mailer/django_email_backend.py
appengine_mailer/gmail.py
appengine_mailer/mail.py
appengine_mailer/main.py
appengine_mailer.egg-info/PKG-INFO
appengine_mailer.egg-info/SOURCES.txt
appengine_mailer.egg-info/dependency_links.txt
appengine_mailer.egg-info/top_level.txt