Metadata-Version: 1.0
Name: appengine-mailer
Version: 0.1
Summary: AppEngine Email Proxy
Home-page: https://github.com/mixcloud/appengine-mailer
Author: Mat Clayton
Author-email: mat@mixcloud.com
License: MIT license, see LICENSE file
Platform: UNKNOWN
